sqlalchemy_psql_upsert/__init__.py
sqlalchemy_psql_upsert/client.py
sqlalchemy_psql_upsert/config.py
sqlalchemy_psql_upsert/py.typed
sqlalchemy_psql_upsert-1.3.0.dist-info/LICENSE
sqlalchemy_psql_upsert-1.3.0.dist-info/METADATA
sqlalchemy_psql_upsert-1.3.0.dist-info/WHEEL
sqlalchemy_psql_upsert-1.3.0.dist-info/RECORD
