Metadata-Version: 2.3
Name: sqlalchemy-psql-upsert
Version: 1.3.0
Summary: PostgreSQL upsert library with intelligent conflict resolution and multi-threaded processing
License: GPL-3.0
Keywords: postgresql,upsert,sqlalchemy,database,conflict-resolution,bulk-insert,data-migration,pandas
Author: Joao Brito
Requires-Python: >=3.10,<=3.13
Classifier: Development Status :: 5 - Production/Stable
Classifier: Intended Audience :: Developers
Classifier: Intended Audience :: System Administrators
Classifier: License :: OSI Approved :: GNU General Public License v3 (GPLv3)
Classifier: Operating System :: OS Independent
Classifier: Programming Language :: Python :: 3
Classifier: Programming Language :: Python :: 3.10
Classifier: Programming Language :: Python :: 3.11
Classifier: Programming Language :: Python :: 3.12
Classifier: Programming Language :: Python :: 3.13
Classifier: Topic :: Database
Classifier: Topic :: Database :: Database Engines/Servers
Classifier: Topic :: Software Development :: Libraries :: Python Modules
Classifier: Topic :: System :: Systems Administration
Classifier: Typing :: Typed
Requires-Dist: SQLAlchemy (>=2.0.41,<3.0.0)
Requires-Dist: pandas (>=2.3.1,<3.0.0)
Requires-Dist: psycopg2-binary (>=2.9.10,<3.0.0)
Requires-Dist: python-dotenv (>=1.1.1,<2.0.0)
Requires-Dist: tqdm (>=4.67.1,<5.0.0)
Project-URL: Homepage, https://github.com/machado000/sqlalchemy-psql-upsert
Project-URL: Issues, https://github.com/machado000/sqlalchemy-psql-upsert/issues
